openmodule_commands/__init__.py
openmodule_commands/translate.py
openmodule_commands-16.0.5.dist-info/METADATA
openmodule_commands-16.0.5.dist-info/WHEEL
openmodule_commands-16.0.5.dist-info/entry_points.txt
openmodule_commands-16.0.5.dist-info/top_level.txt
openmodule_commands-16.0.5.dist-info/RECORD
