Metadata-Version: 2.4
Name: openmodule_commands
Version: 16.0.5
Summary: Commands for openmodule services
Home-page: https://gitlab.com/arivo-public/device-python/openmodule.git
Author: ARIVO
Author-email: support@arivo.co
License: GNU General Public License v2 (GPLv2)
Keywords: arivo openmodule openmodule_commands commands
Classifier: Intended Audience :: Developers
Classifier: License :: OSI Approved :: GNU General Public License v2 (GPLv2)
Classifier: Programming Language :: Python
Classifier: Programming Language :: Python :: 3.12
Requires-Dist: pyyaml<7,>=5.0
Dynamic: author
Dynamic: author-email
Dynamic: classifier
Dynamic: home-page
Dynamic: keywords
Dynamic: license
Dynamic: requires-dist
Dynamic: summary
